Metadata-Version: 2.1
Name: alacritty-color-switcher
Version: 0.1.3
Summary: Apply color schemes to your alacritty config.
Home-page: https://github.com/tbehner/alacritty-color-switcher
Author: Timm Behner
Author-email: behner@cs.uni-bonn.de
License: UNKNOWN
Platform: UNKNOWN
Classifier: License :: OSI Approved :: GNU General Public License v3 (GPLv3)
Classifier: Programming Language :: Python :: 3.7
